Constrained_GaussianProcess/_GibbsSampler.py
Constrained_GaussianProcess/_HmcSampler.py
Constrained_GaussianProcess/_MHSampler.py
Constrained_GaussianProcess/_RSM.py
Constrained_GaussianProcess/__init__.py
Constrained_GaussianProcess/_constrained_gp.py
Constrained_GaussianProcess/_rtmg.py
Constrained_GaussianProcess/test.py
Constrained_GaussianProcess-0.1.1.dist-info/LICENSE
Constrained_GaussianProcess-0.1.1.dist-info/METADATA
Constrained_GaussianProcess-0.1.1.dist-info/WHEEL
Constrained_GaussianProcess-0.1.1.dist-info/top_level.txt
Constrained_GaussianProcess-0.1.1.dist-info/RECORD
