Metadata-Version: 2.1
Name: Constrained-GaussianProcess
Version: 0.1.1
Summary: Implementation of Python package for Fitting and Inference of Linearly Constrained Gaussian Processes
Home-page: https://gitlab.inf.ethz.ch/mmutny/contrained-gps
Author: Liaowang Huang
Author-email: liahuang@student.ethz.ch
License: UNKNOWN
Platform: UNKNOWN
Classifier: Programming Language :: Python :: 3
Classifier: License :: OSI Approved :: MIT License
Classifier: Operating System :: OS Independent
Requires-Python: >=3.7
